setup.py
common_utils_pkg/__init__.py
common_utils_pkg/__main__.py
common_utils_pkg.egg-info/PKG-INFO
common_utils_pkg.egg-info/SOURCES.txt
common_utils_pkg.egg-info/dependency_links.txt
common_utils_pkg.egg-info/requires.txt
common_utils_pkg.egg-info/top_level.txt
common_utils_pkg/prices_utils/__init__.py
common_utils_pkg/prices_utils/formatters.py
common_utils_pkg/prices_utils/price_database_async.py
common_utils_pkg/prices_utils/types.py
common_utils_pkg/prices_utils/utils.py
common_utils_pkg/types/__init__.py
common_utils_pkg/types/binance_types.py
common_utils_pkg/types/types.py
common_utils_pkg/utils/__init__.py
common_utils_pkg/utils/api_server.py
common_utils_pkg/utils/aws_adapter.py
common_utils_pkg/utils/database.py
common_utils_pkg/utils/deprecated_logger.py
common_utils_pkg/utils/deprecated_notifications.py
common_utils_pkg/utils/graceful_killer.py
common_utils_pkg/utils/logger.py
common_utils_pkg/utils/notifications.py
common_utils_pkg/utils/scheduler.py
common_utils_pkg/utils/security.py
common_utils_pkg/utils/telemetry.py
common_utils_pkg/utils/utils.py