Metadata-Version: 2.1
Name: common-utils-pkg
Version: 0.2.28
Summary: Common utils package. With some basic classes.
Author: John Johny
Author-email: love.dev.2020@email.com
Keywords: python
Classifier: Development Status :: 3 - Alpha
Classifier: Intended Audience :: Education
Classifier: Programming Language :: Python :: 2
Classifier: Programming Language :: Python :: 3
Classifier: Operating System :: MacOS :: MacOS X
